createrepo_c/__init__.py
createrepo_c/_createrepo_c.so
createrepo_c/data/bin/createrepo_c
createrepo_c/data/bin/mergerepo_c
createrepo_c/data/bin/modifyrepo_c
createrepo_c/data/bin/sqliterepo_c
createrepo_c.libs/libacl-77cc55e2.so.1.1.2253
createrepo_c.libs/libattr-77508b02.so.1.1.2448
createrepo_c.libs/libaudit-bce81ef2.so.1.0.0
createrepo_c.libs/libblkid-e4a77f31.so.1.1.0
createrepo_c.libs/libbrotlicommon-b6e6c8bd.so.1.0.6
createrepo_c.libs/libbrotlidec-5094ef0a.so.1.0.6
createrepo_c.libs/libbz2-549b318a.so.1.0.6
createrepo_c.libs/libcap-f91f74e2.so.2.48
createrepo_c.libs/libcap-ng-3db0a01e.so.0.0.0
createrepo_c.libs/libcom_err-4a1178d7.so.2.1
createrepo_c.libs/libcrypt-258f54d5.so.1.1.0
createrepo_c.libs/libcrypto-3eda328c.so.1.1.1k
createrepo_c.libs/libcurl-7faeef02.so.4.5.0
createrepo_c.libs/libdb-5-857b088e.3.so
createrepo_c.libs/libelf-0-5aa9f2f1.190.so
createrepo_c.libs/libffi-b23fa0bb.so.6.0.2
createrepo_c.libs/libgio-2-f906df97.0.so.0.5600.4
createrepo_c.libs/libgmodule-2-363abcca.0.so.0.5600.4
createrepo_c.libs/libgmp-6d1678ee.so.10.3.2
createrepo_c.libs/libgnutls-0fce6148.so.30.28.2
createrepo_c.libs/libgssapi_krb5-c364e5ca.so.2.2
createrepo_c.libs/libhogweed-2f02f501.so.4.5
createrepo_c.libs/libidn2-1b2a13b7.so.0.3.6
createrepo_c.libs/libk5crypto-05068f8e.so.3.1
createrepo_c.libs/libkeyutils-fe6e95a9.so.1.6
createrepo_c.libs/libkrb5-9cbf5f3f.so.3.3
createrepo_c.libs/libkrb5support-3e3b7751.so.0.1
createrepo_c.libs/liblber-2-86b08e65.4.so.2.10.9
createrepo_c.libs/libldap-2-5c1dd279.4.so.2.10.9
createrepo_c.libs/liblua-5-e9f6106b.3.so
createrepo_c.libs/liblzma-6f9d2abe.so.5.2.4
createrepo_c.libs/libmagic-55d818ac.so.1.0.0
createrepo_c.libs/libmodulemd-86d650cd.so.2.13.0
createrepo_c.libs/libmount-bbb803f3.so.1.1.0
createrepo_c.libs/libnettle-f004dfb3.so.6.5
createrepo_c.libs/libnghttp2-3a94c239.so.14.17.0
createrepo_c.libs/libp11-kit-7399a377.so.0.3.0
createrepo_c.libs/libpcre-1e9fb62f.so.1.2.10
createrepo_c-1.2.2.dist-info/METADATA
createrepo_c-1.2.2.dist-info/WHEEL
createrepo_c-1.2.2.dist-info/entry_points.txt
createrepo_c-1.2.2.dist-info/top_level.txt
createrepo_c-1.2.2.dist-info/RECORD
createrepo_c-1.2.2.dist-info/licenses/AUTHORS
createrepo_c-1.2.2.dist-info/licenses/COPYING
